notificator/__init__.py
notificator/email_processor.py
notificator/notificator.py
notificator_yandprakt_middle_python-0.0.5.dist-info/LICENSE
notificator_yandprakt_middle_python-0.0.5.dist-info/METADATA
notificator_yandprakt_middle_python-0.0.5.dist-info/WHEEL
notificator_yandprakt_middle_python-0.0.5.dist-info/top_level.txt
notificator_yandprakt_middle_python-0.0.5.dist-info/RECORD
