Metadata-Version: 2.1
Name: notificator-yandprakt-middle-python
Version: 0.0.5
Summary: Notificator for inner ussage
Home-page: https://github.com/RomanAVolodin/notificator_middle_python
Author: Roman Volodin
Author-email: rozarioagro@gmail.com
License: UNKNOWN
Platform: UNKNOWN
Classifier: Programming Language :: Python :: 3.9
Classifier: License :: OSI Approved :: MIT License
Classifier: Operating System :: OS Independent
Requires-Python: >=3.8
License-File: LICENSE
Requires-Dist: certifi (==2020.12.5)
Requires-Dist: Jinja2 (==3.0.1)
Requires-Dist: MarkupSafe (==2.0.1)
Requires-Dist: pika (==1.2.0)
Requires-Dist: psycopg2-binary (==2.9.3)
Requires-Dist: pydantic (==1.8.1)
Requires-Dist: python-logstash (==0.4.6)
Requires-Dist: sentry-sdk (==1.3.0)
Requires-Dist: typing-extensions (==3.7.4.3)
Requires-Dist: urllib3 (==1.26.4)
